beryl_plugin/__init__.py
beryl_plugin/listeners.py
beryl_plugin-0.0.1.dist-info/LICENSE
beryl_plugin-0.0.1.dist-info/METADATA
beryl_plugin-0.0.1.dist-info/WHEEL
beryl_plugin-0.0.1.dist-info/top_level.txt
beryl_plugin-0.0.1.dist-info/RECORD
