Metadata-Version: 2.1
Name: beryl-plugin
Version: 0.0.1
Summary: A helper library for creating plugins for the Beryl Timing System.
Home-page: http://github.com/BrenekH/beryl_plugin
Author: Brenek Harrison
Author-email: brenekharrison@gmail.com
License: MIT
Platform: UNKNOWN
Classifier: Programming Language :: Python :: 3
Classifier: License :: OSI Approved :: MIT License
Classifier: Operating System :: OS Independent
Requires-Python: >=3.6
